panoramic/auth/__init__.py
panoramic/auth/client.py
panoramic/auth/py.typed
panoramic_auth-1.0.0.dist-info/METADATA
panoramic_auth-1.0.0.dist-info/WHEEL
panoramic_auth-1.0.0.dist-info/top_level.txt
panoramic_auth-1.0.0.dist-info/RECORD
