Metadata-Version: 2.1
Name: panoramic-auth
Version: 1.0.0
Summary: Panoramic Authentication SDK
Home-page: https://github.com/panoramichq/panoramic-auth-py
Author: Panoramic
Maintainer: Panoramic
License: UNKNOWN
Project-URL: Source Code, https://github.com/panoramichq/panoramic-auth-py
Keywords: panoramic,authentication,sdk
Platform: UNKNOWN
Classifier: Development Status :: 5 - Production/Stable
Classifier: Environment :: Web Environment
Classifier: Intended Audience :: Developers
Classifier: License :: OSI Approved
Classifier: License :: OSI Approved :: MIT License
Classifier: Operating System :: MacOS
Classifier: Operating System :: POSIX
Classifier: Operating System :: POSIX :: Linux
Classifier: Programming Language :: Python
Classifier: Programming Language :: Python :: 3
Classifier: Programming Language :: Python :: 3.6
Classifier: Programming Language :: Python :: 3.7
Classifier: Programming Language :: Python :: 3.8
Classifier: Programming Language :: Python :: 3 :: Only
Classifier: Programming Language :: Python :: Implementation
Classifier: Programming Language :: Python :: Implementation :: CPython
Classifier: Programming Language :: Python :: Implementation :: PyPy
Classifier: Topic :: Software Development :: Libraries :: Python Modules
Requires-Python: >=3.6
Requires-Dist: requests-oauthlib (>=1.3.0)
Provides-Extra: dev
Requires-Dist: pytest (>=5.3.5) ; extra == 'dev'
Requires-Dist: responses (>=0.10.14) ; extra == 'dev'
Requires-Dist: freezegun (>=0.3.15) ; extra == 'dev'
Requires-Dist: pre-commit (>=2.1.1) ; extra == 'dev'
Provides-Extra: tests
Requires-Dist: pytest (>=5.3.5) ; extra == 'tests'
Requires-Dist: responses (>=0.10.14) ; extra == 'tests'
Requires-Dist: freezegun (>=0.3.15) ; extra == 'tests'
